{
  "강철톤 (6세대부터)": {
    "type": ["강철", "땅"],
    "safeType": {
      "노말": 0.5,
      "비행": 0.5,
      "독": 0,
      "바위": 0.25,
      "벌레": 0.5,
      "고스트": 1,
      "강철": 0.5,
      "풀": 1,
      "전기": 0,
      "에스퍼": 0.5,
      "얼음": 1,
      "드래곤": 0.5,
      "악": 1,
      "페어리": 0.5
    },
    "dangerType": { "격투": 2, "땅": 2, "불꽃": 2, "물": 2 },
    "tera": ["강철", "땅"]
  },
  "강철톤 (5세대까지)": {
    "type": ["강철", "땅"],
    "safeType": {
      "노말": 0.5,
      "비행": 0.5,
      "독": 0,
      "바위": 0.25,
      "벌레": 0.5,
      "고스트": 0.5,
      "강철": 0.5,
      "풀": 1,
      "전기": 0,
      "에스퍼": 0.5,
      "얼음": 1,
      "드래곤": 0.5,
      "악": 0.5,
      "페어리": 1
    },
    "dangerType": { "격투": 2, "땅": 2, "불꽃": 2, "물": 2 },
    "tera": ["강철", "땅"]
  },
  "거대코뿌리": {
    "type": ["땅", "바위"],
    "safeType": {
      "노말": 0.5,
      "비행": 0.5,
      "독": 0.25,
      "바위": 0.5,
      "벌레": 1,
      "고스트": 1,
      "불꽃": 0.5,
      "전기": 0,
      "에스퍼": 1,
      "드래곤": 1,
      "악": 1,
      "페어리": 1
    },
    "dangerType": {
      "격투": 2,
      "땅": 2,
      "강철": 2,
      "물": 4,
      "풀": 4,
      "얼음": 2
    },
    "tera": ["땅", "바위"]
  },
  "고지": {
    "type": ["땅"],
    "safeType": {
      "노말": 1,
      "격투": 1,
      "비행": 1,
      "독": 0.5,
      "땅": 1,
      "바위": 0.5,
      "벌레": 1,
      "고스트": 1,
      "강철": 1,
      "불꽃": 1,
      "전기": 0,
      "에스퍼": 1,
      "드래곤": 1,
      "악": 1,
      "페어리": 1
    },
    "dangerType": { "물": 2, "풀": 2, "얼음": 2 },
    "tera": ["땅"]
  },
  "고지 (알로라 고지)": {
    "type": ["땅"],
    "safeType": {
      "노말": 0.5,
      "비행": 0.5,
      "독": 0,
      "바위": 1,
      "벌레": 0.5,
      "고스트": 1,
      "강철": 1,
      "물": 1,
      "풀": 0.5,
      "전기": 1,
      "에스퍼": 0.5,
      "얼음": 0.25,
      "드래곤": 0.5,
      "악": 1,
      "페어리": 0.5
    },
    "dangerType": { "격투": 4, "땅": 2, "불꽃": 4 },
    "tera": ["땅"]
  },
  "골루그": {
    "type": ["땅", "고스트"],
    "safeType": {
      "노말": 0,
      "격투": 0,
      "비행": 1,
      "독": 0.25,
      "땅": 1,
      "바위": 0.5,
      "벌레": 0.5,
      "강철": 1,
      "불꽃": 1,
      "전기": 0,
      "에스퍼": 1,
      "드래곤": 1,
      "페어리": 1
    },
    "dangerType": { "고스트": 2, "물": 2, "풀": 2, "얼음": 2, "악": 2 },
    "tera": ["땅", "고스트"]
  },
  "골비람": {
    "type": ["땅", "고스트"],
    "safeType": {
      "노말": 0,
      "격투": 0,
      "비행": 1,
      "독": 0.25,
      "땅": 1,
      "바위": 0.5,
      "벌레": 0.5,
      "강철": 1,
      "불꽃": 1,
      "전기": 0,
      "에스퍼": 1,
      "드래곤": 1,
      "페어리": 1
    },
    "dangerType": { "고스트": 2, "물": 2, "풀": 2, "얼음": 2, "악": 2 },
    "tera": ["땅", "고스트"]
  },
  "그란돈": {
    "type": ["땅"],
    "safeType": {
      "노말": 1,
      "격투": 1,
      "비행": 1,
      "독": 0.5,
      "땅": 1,
      "바위": 0.5,
      "벌레": 1,
      "고스트": 1,
      "강철": 1,
      "불꽃": 1,
      "전기": 0,
      "에스퍼": 1,
      "드래곤": 1,
      "악": 1,
      "페어리": 1
    },
    "dangerType": { "물": 2, "풀": 2, "얼음": 2 },
    "tera": ["땅"]
  },
  "그란돈 (원시그란돈)": {
    "type": ["땅"],
    "safeType": {
      "노말": 1,
      "격투": 1,
      "비행": 1,
      "독": 0.5,
      "바위": 1,
      "벌레": 0.5,
      "고스트": 1,
      "강철": 0.5,
      "불꽃": 0.5,
      "풀": 1,
      "전기": 0,
      "에스퍼": 1,
      "얼음": 1,
      "드래곤": 1,
      "악": 1,
      "페어리": 0.5
    },
    "dangerType": { "땅": 2, "물": 4 },
    "tera": ["땅"]
  },
  "글라이거": {
    "type": ["땅", "비행"],
    "safeType": {
      "노말": 1,
      "격투": 0.5,
      "비행": 1,
      "독": 0.5,
      "땅": 0,
      "바위": 1,
      "벌레": 0.5,
      "고스트": 1,
      "강철": 1,
      "불꽃": 1,
      "풀": 1,
      "전기": 0,
      "에스퍼": 1,
      "드래곤": 1,
      "악": 1,
      "페어리": 1
    },
    "dangerType": { "물": 2, "얼음": 4 },
    "tera": ["땅", "비행"]
  },
  "글라이온": {
    "type": ["땅", "비행"],
    "safeType": {
      "노말": 1,
      "격투": 0.5,
      "비행": 1,
      "독": 0.5,
      "땅": 0,
      "바위": 1,
      "벌레": 0.5,
      "고스트": 1,
      "강철": 1,
      "불꽃": 1,
      "풀": 1,
      "전기": 0,
      "에스퍼": 1,
      "드래곤": 1,
      "악": 1,
      "페어리": 1
    },
    "dangerType": { "물": 2, "얼음": 4 },
    "tera": ["땅", "비행"]
  },
  "깜눈크": {
    "type": ["땅", "악"],
    "safeType": {
      "노말": 1,
      "비행": 1,
      "독": 0.5,
      "땅": 1,
      "바위": 0.5,
      "고스트": 0.5,
      "강철": 1,
      "불꽃": 1,
      "전기": 0,
      "에스퍼": 0,
      "드래곤": 1,
      "악": 0.5
    },
    "dangerType": {
      "격투": 2,
      "벌레": 2,
      "물": 2,
      "풀": 2,
      "얼음": 2,
      "페어리": 2
    },
    "tera": ["땅", "악"]
  },
  "꼬마돌": {
    "type": ["바위", "땅"],
    "safeType": {
      "노말": 0.5,
      "비행": 0.5,
      "독": 0.25,
      "바위": 0.5,
      "벌레": 1,
      "고스트": 1,
      "불꽃": 0.5,
      "전기": 0,
      "에스퍼": 1,
      "드래곤": 1,
      "악": 1,
      "페어리": 1
    },
    "dangerType": {
      "격투": 2,
      "땅": 2,
      "강철": 2,
      "물": 4,
      "풀": 4,
      "얼음": 2
    },
    "tera": ["바위", "땅"]
  },
  "꼬마돌 (알로라 꼬마돌)": {
    "type": ["바위", "땅"],
    "safeType": {
      "노말": 0.5,
      "비행": 0.25,
      "독": 0.5,
      "바위": 1,
      "벌레": 1,
      "고스트": 1,
      "강철": 1,
      "불꽃": 0.5,
      "전기": 0.5,
      "에스퍼": 1,
      "얼음": 1,
      "드래곤": 1,
      "악": 1,
      "페어리": 1
    },
    "dangerType": { "격투": 2, "땅": 4, "물": 2, "풀": 2 },
    "tera": ["바위", "땅"]
  },
  "꾸꾸리": {
    "type": ["얼음", "땅"],
    "safeType": {
      "노말": 1,
      "비행": 1,
      "독": 0.5,
      "땅": 1,
      "바위": 1,
      "벌레": 1,
      "고스트": 1,
      "전기": 0,
      "에스퍼": 1,
      "얼음": 1,
      "드래곤": 1,
      "악": 1,
      "페어리": 1
    },
    "dangerType": { "격투": 2, "강철": 2, "불꽃": 2, "물": 2, "풀": 2 },
    "tera": ["얼음", "땅"]
  },
  "누오": {
    "type": ["물", "땅"],
    "safeType": {
      "노말": 1,
      "격투": 1,
      "비행": 1,
      "독": 0.5,
      "땅": 1,
      "바위": 0.5,
      "벌레": 1,
      "고스트": 1,
      "강철": 0.5,
      "불꽃": 0.5,
      "물": 1,
      "전기": 0,
      "에스퍼": 1,
      "얼음": 1,
      "드래곤": 1,
      "악": 1,
      "페어리": 1
    },
    "dangerType": { "풀": 4 },
    "tera": ["물", "땅"]
  },
  "늪짱이": {
    "type": ["물", "땅"],
    "safeType": {
      "노말": 1,
      "격투": 1,
      "비행": 1,
      "독": 0.5,
      "땅": 1,
      "바위": 0.5,
      "벌레": 1,
      "고스트": 1,
      "강철": 0.5,
      "불꽃": 0.5,
      "물": 1,
      "전기": 0,
      "에스퍼": 1,
      "얼음": 1,
      "드래곤": 1,
      "악": 1,
      "페어리": 1
    },
    "dangerType": { "풀": 4 },
    "tera": ["물", "땅"]
  },
  "니드퀸": {
    "type": ["독", "땅"],
    "safeType": {
      "노말": 1,
      "격투": 0.5,
      "비행": 1,
      "독": 0.25,
      "바위": 0.5,
      "벌레": 0.5,
      "고스트": 1,
      "강철": 1,
      "불꽃": 1,
      "풀": 1,
      "전기": 0,
      "드래곤": 1,
      "악": 1,
      "페어리": 0.5
    },
    "dangerType": { "땅": 2, "물": 2, "에스퍼": 2, "얼음": 2 },
    "tera": ["독", "땅"]
  },
  "니드킹": {
    "type": ["독", "땅"],
    "safeType": {
      "노말": 1,
      "격투": 0.5,
      "비행": 1,
      "독": 0.25,
      "바위": 0.5,
      "벌레": 0.5,
      "고스트": 1,
      "강철": 1,
      "불꽃": 1,
      "풀": 1,
      "전기": 0,
      "드래곤": 1,
      "악": 1,
      "페어리": 0.5
    },
    "dangerType": { "땅": 2, "물": 2, "에스퍼": 2, "얼음": 2 },
    "tera": ["독", "땅"]
  },
  "다투곰": {
    "type": ["땅", "노말"],
    "safeType": {
      "노말": 1,
      "비행": 1,
      "독": 0.5,
      "땅": 1,
      "바위": 0.5,
      "벌레": 1,
      "고스트": 0,
      "강철": 1,
      "불꽃": 1,
      "전기": 0,
      "에스퍼": 1,
      "드래곤": 1,
      "악": 1,
      "페어리": 1
    },
    "dangerType": { "격투": 2, "물": 2, "풀": 2, "얼음": 2 },
    "tera": ["땅", "노말"]
  },
  "닥트리오": {
    "type": ["땅"],
    "safeType": {
      "노말": 1,
      "격투": 1,
      "비행": 1,
      "독": 0.5,
      "땅": 1,
      "바위": 0.5,
      "벌레": 1,
      "고스트": 1,
      "강철": 1,
      "불꽃": 1,
      "전기": 0,
      "에스퍼": 1,
      "드래곤": 1,
      "악": 1,
      "페어리": 1
    },
    "dangerType": { "물": 2, "풀": 2, "얼음": 2 },
    "tera": ["땅"]
  },
  "닥트리오 (알로라 닥트리오)": {
    "type": ["땅"],
    "safeType": {
      "노말": 0.5,
      "비행": 0.5,
      "독": 0,
      "바위": 0.25,
      "벌레": 0.5,
      "고스트": 1,
      "강철": 0.5,
      "풀": 1,
      "전기": 0,
      "에스퍼": 0.5,
      "얼음": 1,
      "드래곤": 0.5,
      "악": 1,
      "페어리": 0.5
    },
    "dangerType": { "격투": 2, "땅": 2, "불꽃": 2, "물": 2 },
    "tera": ["땅"]
  },
  "대짱이": {
    "type": ["물", "땅"],
    "safeType": {
      "노말": 1,
      "격투": 1,
      "비행": 1,
      "독": 0.5,
      "땅": 1,
      "바위": 0.5,
      "벌레": 1,
      "고스트": 1,
      "강철": 0.5,
      "불꽃": 0.5,
      "물": 1,
      "전기": 0,
      "에스퍼": 1,
      "얼음": 1,
      "드래곤": 1,
      "악": 1,
      "페어리": 1
    },
    "dangerType": { "풀": 4 },
    "tera": ["물", "땅"]
  },
  "데구리": {
    "type": ["바위", "땅"],
    "safeType": {
      "노말": 0.5,
      "비행": 0.5,
      "독": 0.25,
      "바위": 0.5,
      "벌레": 1,
      "고스트": 1,
      "불꽃": 0.5,
      "전기": 0,
      "에스퍼": 1,
      "드래곤": 1,
      "악": 1,
      "페어리": 1
    },
    "dangerType": {
      "격투": 2,
      "땅": 2,
      "강철": 2,
      "물": 4,
      "풀": 4,
      "얼음": 2
    },
    "tera": ["바위", "땅"]
  },
  "데구리 (알로라 데구리)": {
    "type": ["바위", "땅"],
    "safeType": {
      "노말": 0.5,
      "비행": 0.25,
      "독": 0.5,
      "바위": 1,
      "벌레": 1,
      "고스트": 1,
      "강철": 1,
      "불꽃": 0.5,
      "전기": 0.5,
      "에스퍼": 1,
      "얼음": 1,
      "드래곤": 1,
      "악": 1,
      "페어리": 1
    },
    "dangerType": { "격투": 2, "땅": 4, "물": 2, "풀": 2 },
    "tera": ["바위", "땅"]
  },
  "데기라스": {
    "type": ["바위", "땅"],
    "safeType": {
      "노말": 0.5,
      "비행": 0.5,
      "독": 0.25,
      "바위": 0.5,
      "벌레": 1,
      "고스트": 1,
      "불꽃": 0.5,
      "전기": 0,
      "에스퍼": 1,
      "드래곤": 1,
      "악": 1,
      "페어리": 1
    },
    "dangerType": {
      "격투": 2,
      "땅": 2,
      "강철": 2,
      "물": 4,
      "풀": 4,
      "얼음": 2
    },
    "tera": ["바위", "땅"]
  },
  "데스마스 (기존폼)": {
    "type": ["고스트"],
    "safeType": {
      "노말": 0,
      "격투": 0,
      "비행": 1,
      "독": 0.5,
      "땅": 1,
      "바위": 1,
      "벌레": 0.5,
      "강철": 1,
      "불꽃": 1,
      "물": 1,
      "풀": 1,
      "전기": 1,
      "에스퍼": 1,
      "얼음": 1,
      "드래곤": 1,
      "페어리": 1
    },
    "dangerType": { "고스트": 2, "악": 2 },
    "tera": ["고스트"]
  },
  "데스마스 (리전폼)": {
    "type": ["고스트"],
    "safeType": {
      "노말": 1,
      "격투": 1,
      "비행": 1,
      "독": 0.25,
      "땅": 1,
      "바위": 0.5,
      "벌레": 0.5,
      "강철": 1,
      "불꽃": 1,
      "전기": 1,
      "에스퍼": 1,
      "드래곤": 1,
      "페어리": 1
    },
    "dangerType": { "고스트": 2, "물": 2, "풀": 2, "얼음": 2, "악": 2 },
    "tera": ["고스트"]
  },
  "데스판": {
    "type": ["땅", "고스트"],
    "safeType": {
      "노말": 1,
      "격투": 1,
      "비행": 1,
      "독": 0.25,
      "땅": 1,
      "바위": 0.5,
      "벌레": 0.5,
      "강철": 1,
      "불꽃": 1,
      "전기": 1,
      "에스퍼": 1,
      "드래곤": 1,
      "페어리": 1
    },
    "dangerType": { "고스트": 2, "물": 2, "풀": 2, "얼음": 2, "악": 2 },
    "tera": ["땅", "고스트"]
  },
  "도롱마담 (초목도롱)": {
    "type": ["벌레", "풀"],
    "safeType": {
      "노말": 1,
      "격투": 0.5,
      "땅": 0.25,
      "고스트": 1,
      "강철": 1,
      "물": 0.5,
      "풀": 0.25,
      "전기": 0.5,
      "에스퍼": 1,
      "드래곤": 1,
      "악": 1,
      "페어리": 1
    },
    "dangerType": {
      "비행": 4,
      "독": 2,
      "바위": 2,
      "벌레": 2,
      "불꽃": 4,
      "얼음": 2
    },
    "tera": ["벌레", "풀"]
  },
  "도롱마담 (모래땅도롱)": {
    "type": ["벌레", "풀"],
    "safeType": {
      "노말": 1,
      "격투": 0.5,
      "독": 0.5,
      "땅": 0.5,
      "바위": 1,
      "벌레": 1,
      "고스트": 1,
      "강철": 1,
      "풀": 1,
      "전기": 0,
      "에스퍼": 1,
      "드래곤": 1,
      "악": 1,
      "페어리": 1
    },
    "dangerType": { "비행": 2, "불꽃": 2, "물": 2, "얼음": 2 },
    "tera": ["벌레", "풀"]
  },
  "도롱마담 (슈레도롱 (6세대부터))": {
    "type": ["벌레", "풀"],
    "safeType": {
      "노말": 0.5,
      "격투": 1,
      "비행": 1,
      "독": 0,
      "땅": 1,
      "바위": 1,
      "벌레": 0.5,
      "고스트": 1,
      "강철": 0.5,
      "물": 1,
      "풀": 0.25,
      "전기": 1,
      "에스퍼": 0.5,
      "얼음": 0.5,
      "드래곤": 0.5,
      "악": 1,
      "페어리": 0.5
    },
    "dangerType": { "불꽃": 4 },
    "tera": ["벌레", "풀"]
  },
  "도롱마담 (슈레도롱 (5세대까지))": {
    "type": ["벌레", "풀"],
    "safeType": {
      "노말": 0.5,
      "격투": 1,
      "비행": 1,
      "독": 0,
      "땅": 1,
      "바위": 1,
      "벌레": 0.5,
      "고스트": 0.5,
      "강철": 0.5,
      "물": 1,
      "풀": 0.25,
      "전기": 1,
      "에스퍼": 0.5,
      "얼음": 0.5,
      "드래곤": 0.5,
      "악": 0.5,
      "페어리": 1
    },
    "dangerType": { "불꽃": 4 },
    "tera": ["벌레", "풀"]
  },
  "두까비": {
    "type": ["물", "땅"],
    "safeType": {
      "노말": 1,
      "격투": 1,
      "비행": 1,
      "독": 0.5,
      "땅": 1,
      "바위": 0.5,
      "벌레": 1,
      "고스트": 1,
      "강철": 0.5,
      "불꽃": 0.5,
      "물": 1,
      "전기": 0,
      "에스퍼": 1,
      "얼음": 1,
      "드래곤": 1,
      "악": 1,
      "페어리": 1
    },
    "dangerType": { "풀": 4 },
    "tera": ["물", "땅"]
  },
  "두더류": {
    "type": ["땅"],
    "safeType": {
      "노말": 1,
      "격투": 1,
      "비행": 1,
      "독": 0.5,
      "땅": 1,
      "바위": 0.5,
      "벌레": 1,
      "고스트": 1,
      "강철": 1,
      "불꽃": 1,
      "전기": 0,
      "에스퍼": 1,
      "드래곤": 1,
      "악": 1,
      "페어리": 1
    },
    "dangerType": { "물": 2, "풀": 2, "얼음": 2 },
    "tera": ["땅"]
  },
  "두빅굴": {
    "type": ["물", "땅"],
    "safeType": {
      "노말": 1,
      "격투": 1,
      "비행": 1,
      "독": 0.5,
      "땅": 1,
      "바위": 0.5,
      "벌레": 1,
      "고스트": 1,
      "강철": 0.5,
      "불꽃": 0.5,
      "물": 1,
      "전기": 0,
      "에스퍼": 1,
      "얼음": 1,
      "드래곤": 1,
      "악": 1,
      "페어리": 1
    },
    "dangerType": { "풀": 4 },
    "tera": ["물", "땅"]
  },
  "둔타": {
    "type": ["불꽃", "땅"],
    "safeType": {
      "노말": 1,
      "격투": 1,
      "비행": 1,
      "독": 0.5,
      "바위": 1,
      "벌레": 0.5,
      "고스트": 1,
      "강철": 0.5,
      "불꽃": 0.5,
      "풀": 1,
      "전기": 0,
      "에스퍼": 1,
      "얼음": 1,
      "드래곤": 1,
      "악": 1,
      "페어리": 0.5
    },
    "dangerType": { "땅": 2, "물": 4 },
    "tera": ["불꽃", "땅"]
  },
  "들눈해": {
    "type": ["땅", "풀"],
    "safeType": {
      "노말": 1,
      "격투": 1,
      "독": 1,
      "땅": 0.5,
      "바위": 0.5,
      "고스트": 1,
      "강철": 1,
      "물": 1,
      "풀": 1,
      "전기": 0,
      "에스퍼": 1,
      "드래곤": 1,
      "악": 1,
      "페어리": 1
    },
    "dangerType": { "비행": 2, "벌레": 2, "불꽃": 2, "얼음": 4 },
    "tera": ["땅", "풀"]
  },
  "디그다": {
    "type": ["땅"],
    "safeType": {
      "노말": 1,
      "격투": 1,
      "비행": 1,
      "독": 0.5,
      "땅": 1,
      "바위": 0.5,
      "벌레": 1,
      "고스트": 1,
      "강철": 1,
      "불꽃": 1,
      "전기": 0,
      "에스퍼": 1,
      "드래곤": 1,
      "악": 1,
      "페어리": 1
    },
    "dangerType": { "물": 2, "풀": 2, "얼음": 2 },
    "tera": ["땅"]
  },
  "디그다 (알로라 디그다)": {
    "type": ["땅"],
    "safeType": {
      "노말": 0.5,
      "비행": 0.5,
      "독": 0,
      "바위": 0.25,
      "벌레": 0.5,
      "고스트": 1,
      "강철": 0.5,
      "풀": 1,
      "전기": 0,
      "에스퍼": 0.5,
      "얼음": 1,
      "드래곤": 0.5,
      "악": 1,
      "페어리": 0.5
    },
    "dangerType": { "격투": 2, "땅": 2, "불꽃": 2, "물": 2 },
    "tera": ["땅"]
  },
  "딥상어동": {
    "type": ["드래곤", "땅"],
    "safeType": {
      "노말": 1,
      "격투": 1,
      "비행": 1,
      "독": 0.5,
      "땅": 1,
      "바위": 0.5,
      "벌레": 1,
      "고스트": 1,
      "강철": 1,
      "불꽃": 0.5,
      "물": 1,
      "풀": 1,
      "전기": 0,
      "에스퍼": 1,
      "악": 1
    },
    "dangerType": { "얼음": 4, "드래곤": 2, "페어리": 2 },
    "tera": ["드래곤", "땅"]
  },
  "딩루": {
    "type": ["악", "땅"],
    "safeType": {
      "노말": 1,
      "비행": 1,
      "독": 0.5,
      "땅": 1,
      "바위": 0.5,
      "고스트": 0.5,
      "강철": 1,
      "불꽃": 1,
      "전기": 0,
      "에스퍼": 0,
      "드래곤": 1,
      "악": 0.5
    },
    "dangerType": {
      "격투": 2,
      "벌레": 2,
      "물": 2,
      "풀": 2,
      "얼음": 2,
      "페어리": 2
    },
    "tera": ["악", "땅"]
  },
  "딱구리": {
    "type": ["바위", "땅"],
    "safeType": {
      "노말": 0.5,
      "비행": 0.5,
      "독": 0.25,
      "바위": 0.5,
      "벌레": 1,
      "고스트": 1,
      "불꽃": 0.5,
      "전기": 0,
      "에스퍼": 1,
      "드래곤": 1,
      "악": 1,
      "페어리": 1
    },
    "dangerType": {
      "격투": 2,
      "땅": 2,
      "강철": 2,
      "물": 4,
      "풀": 4,
      "얼음": 2
    },
    "tera": ["바위", "땅"]
  },
  "딱구리 (알로라 딱구리)": {
    "type": ["바위", "땅"],
    "safeType": {
      "노말": 0.5,
      "비행": 0.25,
      "독": 0.5,
      "바위": 1,
      "벌레": 1,
      "고스트": 1,
      "강철": 1,
      "불꽃": 0.5,
      "전기": 0.5,
      "에스퍼": 1,
      "얼음": 1,
      "드래곤": 1,
      "악": 1,
      "페어리": 1
    },
    "dangerType": { "격투": 2, "땅": 4, "물": 2, "풀": 2 },
    "tera": ["바위", "땅"]
  },
  "랜드로스": {
    "type": ["땅", "비행"],
    "safeType": {
      "노말": 1,
      "격투": 0.5,
      "비행": 1,
      "독": 0.5,
      "땅": 0,
      "바위": 1,
      "벌레": 0.5,
      "고스트": 1,
      "강철": 1,
      "불꽃": 1,
      "풀": 1,
      "전기": 0,
      "에스퍼": 1,
      "드래곤": 1,
      "악": 1,
      "페어리": 1
    },
    "dangerType": { "물": 2, "얼음": 4 },
    "tera": ["땅", "비행"]
  },
  "롱스톤": {
    "type": ["바위", "땅"],
    "safeType": {
      "노말": 0.5,
      "비행": 0.5,
      "독": 0.25,
      "바위": 0.5,
      "벌레": 1,
      "고스트": 1,
      "불꽃": 0.5,
      "전기": 0,
      "에스퍼": 1,
      "드래곤": 1,
      "악": 1,
      "페어리": 1
    },
    "dangerType": {
      "격투": 2,
      "땅": 2,
      "강철": 2,
      "물": 4,
      "풀": 4,
      "얼음": 2
    },
    "tera": ["바위", "땅"]
  },
  "만마드": {
    "type": ["땅"],
    "safeType": {
      "노말": 1,
      "격투": 1,
      "비행": 1,
      "독": 0.5,
      "땅": 1,
      "바위": 0.5,
      "벌레": 1,
      "고스트": 1,
      "강철": 1,
      "불꽃": 1,
      "전기": 0,
      "에스퍼": 1,
      "드래곤": 1,
      "악": 1,
      "페어리": 1
    },
    "dangerType": { "물": 2, "풀": 2, "얼음": 2 },
    "tera": ["땅"]
  },
  "맘모꾸리": {
    "type": ["얼음", "땅"],
    "safeType": {
      "노말": 1,
      "비행": 1,
      "독": 0.5,
      "땅": 1,
      "바위": 1,
      "벌레": 1,
      "고스트": 1,
      "전기": 0,
      "에스퍼": 1,
      "얼음": 1,
      "드래곤": 1,
      "악": 1,
      "페어리": 1
    },
    "dangerType": { "격투": 2, "강철": 2, "불꽃": 2, "물": 2, "풀": 2 },
    "tera": ["얼음", "땅"]
  },
  "머드나기": {
    "type": ["땅"],
    "safeType": {
      "노말": 1,
      "격투": 1,
      "비행": 1,
      "독": 0.5,
      "땅": 1,
      "바위": 0.5,
      "벌레": 1,
      "고스트": 1,
      "강철": 1,
      "불꽃": 1,
      "전기": 0,
      "에스퍼": 1,
      "드래곤": 1,
      "악": 1,
      "페어리": 1
    },
    "dangerType": { "물": 2, "풀": 2, "얼음": 2 },
    "tera": ["땅"]
  },
  "메깅": {
    "type": ["물", "땅"],
    "safeType": {
      "노말": 1,
      "격투": 1,
      "비행": 1,
      "독": 0.5,
      "땅": 1,
      "바위": 0.5,
      "벌레": 1,
      "고스트": 1,
      "강철": 0.5,
      "불꽃": 0.5,
      "물": 1,
      "전기": 0,
      "에스퍼": 1,
      "얼음": 1,
      "드래곤": 1,
      "악": 1,
      "페어리": 1
    },
    "dangerType": { "풀": 4 },
    "tera": ["물", "땅"]
  },
  "메꾸리": {
    "type": ["얼음", "땅"],
    "safeType": {
      "노말": 1,
      "비행": 1,
      "독": 0.5,
      "땅": 1,
      "바위": 1,
      "벌레": 1,
      "고스트": 1,
      "전기": 0,
      "에스퍼": 1,
      "얼음": 1,
      "드래곤": 1,
      "악": 1,
      "페어리": 1
    },
    "dangerType": { "격투": 2, "강철": 2, "불꽃": 2, "물": 2, "풀": 2 },
    "tera": ["얼음", "땅"]
  },
  "메더 (기존폼)": {
    "type": ["땅", "전기"],
    "safeType": {
      "노말": 1,
      "격투": 1,
      "비행": 0.5,
      "독": 0.5,
      "바위": 0.5,
      "벌레": 1,
      "고스트": 1,
      "강철": 0.5,
      "불꽃": 1,
      "전기": 0,
      "에스퍼": 1,
      "드래곤": 1,
      "악": 1,
      "페어리": 1
    },
    "dangerType": { "땅": 2, "물": 2, "풀": 2, "얼음": 2 },
    "tera": ["땅", "전기"]
  },
  "메더 (리전폼)": {
    "type": ["땅", "전기"],
    "safeType": {
      "노말": 0.5,
      "비행": 0.5,
      "독": 0,
      "바위": 0.25,
      "벌레": 0.5,
      "고스트": 1,
      "강철": 0.5,
      "풀": 1,
      "전기": 0,
      "에스퍼": 0.5,
      "얼음": 1,
      "드래곤": 0.5,
      "악": 1,
      "페어리": 0.5
    },
    "dangerType": { "격투": 2, "땅": 2, "불꽃": 2, "물": 2 },
    "tera": ["땅", "전기"]
  },
  "모래꿍": {
    "type": ["고스트", "땅"],
    "safeType": {
      "노말": 0,
      "격투": 0,
      "비행": 1,
      "독": 0.25,
      "땅": 1,
      "바위": 0.5,
      "벌레": 0.5,
      "강철": 1,
      "불꽃": 1,
      "전기": 0,
      "에스퍼": 1,
      "드래곤": 1,
      "페어리": 1
    },
    "dangerType": { "고스트": 2, "물": 2, "풀": 2, "얼음": 2, "악": 2 },
    "tera": ["고스트", "땅"]
  },
  "모래두지": {
    "type": ["땅"],
    "safeType": {
      "노말": 1,
      "격투": 1,
      "비행": 1,
      "독": 0.5,
      "땅": 1,
      "바위": 0.5,
      "벌레": 1,
      "고스트": 1,
      "강철": 1,
      "불꽃": 1,
      "전기": 0,
      "에스퍼": 1,
      "드래곤": 1,
      "악": 1,
      "페어리": 1
    },
    "dangerType": { "물": 2, "풀": 2, "얼음": 2 },
    "tera": ["땅"]
  },
  "모래두지 (알로라 모래두지)": {
    "type": ["땅"],
    "safeType": {
      "노말": 0.5,
      "비행": 0.5,
      "독": 0,
      "바위": 1,
      "벌레": 0.5,
      "고스트": 1,
      "강철": 1,
      "물": 1,
      "풀": 0.5,
      "전기": 1,
      "에스퍼": 0.5,
      "얼음": 0.25,
      "드래곤": 0.5,
      "악": 1,
      "페어리": 0.5
    },
    "dangerType": { "격투": 4, "땅": 2, "불꽃": 4 },
    "tera": ["땅"]
  },
  "모래뱀": {
    "type": ["땅"],
    "safeType": {
      "노말": 1,
      "격투": 1,
      "비행": 1,
      "독": 0.5,
      "땅": 1,
      "바위": 0.5,
      "벌레": 1,
      "고스트": 1,
      "강철": 1,
      "불꽃": 1,
      "전기": 1,
      "에스퍼": 1,
      "드래곤": 1,
      "악": 1,
      "페어리": 1
    },
    "dangerType": { "물": 2, "풀": 2, "얼음": 2 },
    "tera": ["땅"]
  },
  "모래성이당": {
    "type": ["고스트", "땅"],
    "safeType": {
      "노말": 0,
      "격투": 0,
      "비행": 1,
      "독": 0.25,
      "땅": 1,
      "바위": 0.5,
      "벌레": 0.5,
      "강철": 1,
      "불꽃": 1,
      "전기": 0,
      "에스퍼": 1,
      "드래곤": 1,
      "페어리": 1
    },
    "dangerType": { "고스트": 2, "물": 2, "풀": 2, "얼음": 2, "악": 2 },
    "tera": ["고스트", "땅"]
  },
  "모래털가죽": {
    "type": ["전기", "땅"],
    "safeType": {
      "노말": 1,
      "격투": 1,
      "비행": 0.5,
      "독": 0.5,
      "바위": 0.5,
      "벌레": 1,
      "고스트": 1,
      "강철": 0.5,
      "불꽃": 1,
      "전기": 0,
      "에스퍼": 1,
      "드래곤": 1,
      "악": 1,
      "페어리": 1
    },
    "dangerType": { "땅": 2, "물": 2, "풀": 2, "얼음": 2 },
    "tera": ["전기", "땅"]
  },
  "몰드류 (6세대부터)": {
    "type": ["땅", "강철"],
    "safeType": {
      "노말": 0.5,
      "비행": 0.5,
      "독": 0,
      "바위": 0.25,
      "벌레": 0.5,
      "고스트": 1,
      "강철": 0.5,
      "풀": 1,
      "전기": 0,
      "에스퍼": 0.5,
      "얼음": 1,
      "드래곤": 0.5,
      "악": 1,
      "페어리": 0.5
    },
    "dangerType": { "격투": 2, "땅": 2, "불꽃": 2, "물": 2 },
    "tera": ["땅", "강철"]
  },
  "몰드류 (5세대까지)": {
    "type": ["땅", "강철"],
    "safeType": {
      "노말": 0.5,
      "비행": 0.5,
      "독": 0,
      "바위": 0.25,
      "벌레": 0.5,
      "고스트": 0.5,
      "강철": 0.5,
      "풀": 1,
      "전기": 0,
      "에스퍼": 0.5,
      "얼음": 1,
      "드래곤": 0.5,
      "악": 0.5,
      "페어리": 0.5
    },
    "dangerType": { "격투": 2, "땅": 2, "불꽃": 2, "물": 2 },
    "tera": ["땅", "강철"]
  },
  "무쇠바퀴": {
    "type": ["땅", "강철"],
    "safeType": {
      "노말": 0.5,
      "비행": 0.5,
      "독": 0,
      "바위": 0.25,
      "벌레": 0.5,
      "고스트": 1,
      "강철": 0.5,
      "풀": 1,
      "전기": 0,
      "에스퍼": 0.5,
      "얼음": 1,
      "드래곤": 0.5,
      "악": 1,
      "페어리": 0.5
    },
    "dangerType": { "격투": 2, "땅": 2, "불꽃": 2, "물": 2 },
    "tera": ["땅", "강철"]
  },
  "미꾸리": {
    "type": ["물", "땅"],
    "safeType": {
      "노말": 1,
      "격투": 1,
      "비행": 1,
      "독": 0.5,
      "땅": 1,
      "바위": 0.5,
      "벌레": 1,
      "고스트": 1,
      "강철": 0.5,
      "불꽃": 0.5,
      "물": 1,
      "전기": 0,
      "에스퍼": 1,
      "얼음": 1,
      "드래곤": 1,
      "악": 1,
      "페어리": 1
    },
    "dangerType": { "풀": 4 },
    "tera": ["물", "땅"]
  },
  "비브라바": {
    "type": ["땅", "드래곤"],
    "safeType": {
      "노말": 1,
      "격투": 1,
      "비행": 1,
      "독": 0.5,
      "땅": 1,
      "바위": 0.5,
      "벌레": 1,
      "고스트": 1,
      "강철": 1,
      "불꽃": 0.5,
      "물": 1,
      "풀": 1,
      "전기": 0,
      "에스퍼": 1,
      "악": 1
    },
    "dangerType": { "얼음": 4, "드래곤": 2, "페어리": 2 },
    "tera": ["땅", "드래곤"]
  },
  "뿔카노": {
    "type": ["땅", "바위"],
    "safeType": {
      "노말": 0.5,
      "비행": 0.5,
      "독": 0.25,
      "바위": 0.5,
      "벌레": 1,
      "고스트": 1,
      "불꽃": 0.5,
      "전기": 0,
      "에스퍼": 1,
      "드래곤": 1,
      "악": 1,
      "페어리": 1
    },
    "dangerType": {
      "격투": 2,
      "땅": 2,
      "강철": 2,
      "물": 4,
      "풀": 4,
      "얼음": 2
    },
    "tera": ["땅", "바위"]
  },
  "사다이사": {
    "type": ["땅"],
    "safeType": {
      "노말": 1,
      "격투": 1,
      "비행": 1,
      "독": 0.5,
      "땅": 1,
      "바위": 0.5,
      "벌레": 1,
      "고스트": 1,
      "강철": 1,
      "불꽃": 1,
      "전기": 1,
      "에스퍼": 1,
      "드래곤": 1,
      "악": 1,
      "페어리": 1
    },
    "dangerType": { "물": 2, "풀": 2, "얼음": 2 },
    "tera": ["땅"]
  },
  "악비르": {
    "type": ["땅", "악"],
    "safeType": {
      "노말": 1,
      "비행": 1,
      "독": 0.5,
      "땅": 1,
      "바위": 0.5,
      "고스트": 0.5,
      "강철": 1,
      "불꽃": 1,
      "전기": 0,
      "에스퍼": 0,
      "드래곤": 1,
      "악": 0.5
    },
    "dangerType": {
      "격투": 2,
      "벌레": 2,
      "물": 2,
      "풀": 2,
      "얼음": 2,
      "페어리": 2
    },
    "tera": ["땅", "악"]
  },
  "악비아르": {
    "type": ["땅", "악"],
    "safeType": {
      "노말": 1,
      "비행": 1,
      "독": 0.5,
      "땅": 1,
      "바위": 0.5,
      "고스트": 0.5,
      "강철": 1,
      "불꽃": 1,
      "전기": 0,
      "에스퍼": 0,
      "드래곤": 1,
      "악": 0.5
    },
    "dangerType": {
      "격투": 2,
      "벌레": 2,
      "물": 2,
      "풀": 2,
      "얼음": 2,
      "페어리": 2
    },
    "tera": ["땅", "악"]
  },
  "애버라스": {
    "type": ["바위", "땅"],
    "safeType": {
      "노말": 0.5,
      "비행": 0.5,
      "독": 0.25,
      "바위": 0.5,
      "벌레": 1,
      "고스트": 1,
      "불꽃": 0.5,
      "전기": 0,
      "에스퍼": 1,
      "드래곤": 1,
      "악": 1,
      "페어리": 1
    },
    "dangerType": {
      "격투": 2,
      "땅": 2,
      "강철": 2,
      "물": 4,
      "풀": 4,
      "얼음": 2
    },
    "tera": ["바위", "땅"]
  },
  "오뚝군": {
    "type": ["땅", "에스퍼"],
    "safeType": {
      "노말": 1,
      "격투": 0.5,
      "비행": 1,
      "독": 0.5,
      "땅": 1,
      "바위": 0.5,
      "강철": 1,
      "불꽃": 1,
      "전기": 0,
      "에스퍼": 0.5,
      "드래곤": 1,
      "페어리": 1
    },
    "dangerType": {
      "벌레": 2,
      "고스트": 2,
      "물": 2,
      "풀": 2,
      "얼음": 2,
      "악": 2
    },
    "tera": ["땅", "에스퍼"]
  },
  "우파": {
    "type": ["물", "땅"],
    "safeType": {
      "노말": 1,
      "격투": 1,
      "비행": 1,
      "독": 0.5,
      "땅": 1,
      "바위": 0.5,
      "벌레": 1,
      "고스트": 1,
      "강철": 0.5,
      "불꽃": 0.5,
      "물": 1,
      "전기": 0,
      "에스퍼": 1,
      "얼음": 1,
      "드래곤": 1,
      "악": 1,
      "페어리": 1
    },
    "dangerType": { "풀": 4 },
    "tera": ["물", "땅"]
  },
  "우파 (팔데아 우파)": {
    "type": ["물", "땅"],
    "safeType": {
      "노말": 1,
      "격투": 0.5,
      "비행": 1,
      "독": 0.25,
      "바위": 0.5,
      "벌레": 0.5,
      "고스트": 1,
      "강철": 1,
      "불꽃": 1,
      "풀": 1,
      "전기": 0,
      "드래곤": 1,
      "악": 1,
      "페어리": 0.5
    },
    "dangerType": { "땅": 2, "물": 2, "에스퍼": 2, "얼음": 2 },
    "tera": ["물", "땅"]
  },
  "위대한엄니": {
    "type": ["땅", "격투"],
    "safeType": {
      "노말": 1,
      "격투": 1,
      "독": 0.5,
      "땅": 1,
      "바위": 0.25,
      "벌레": 0.5,
      "고스트": 1,
      "강철": 1,
      "불꽃": 1,
      "전기": 0,
      "드래곤": 1,
      "악": 0.5
    },
    "dangerType": {
      "비행": 2,
      "물": 2,
      "풀": 2,
      "에스퍼": 2,
      "얼음": 2,
      "페어리": 2
    },
    "tera": ["땅", "격투"]
  },
  "육파리": {
    "type": ["땅", "풀"],
    "safeType": {
      "노말": 1,
      "격투": 1,
      "독": 1,
      "땅": 0.5,
      "바위": 0.5,
      "고스트": 1,
      "강철": 1,
      "물": 1,
      "풀": 1,
      "전기": 0,
      "에스퍼": 1,
      "드래곤": 1,
      "악": 1,
      "페어리": 1
    },
    "dangerType": { "비행": 2, "벌레": 2, "불꽃": 2, "얼음": 4 },
    "tera": ["땅", "풀"]
  },
  "점토도리": {
    "type": ["땅", "에스퍼"],
    "safeType": {
      "노말": 1,
      "격투": 0.5,
      "비행": 1,
      "독": 0.5,
      "땅": 1,
      "바위": 0.5,
      "강철": 1,
      "불꽃": 1,
      "전기": 0,
      "에스퍼": 0.5,
      "드래곤": 1,
      "페어리": 1
    },
    "dangerType": {
      "벌레": 2,
      "고스트": 2,
      "물": 2,
      "풀": 2,
      "얼음": 2,
      "악": 2
    },
    "tera": ["땅", "에스퍼"]
  },
  "지가르데": {
    "type": ["드래곤", "땅"],
    "safeType": {
      "노말": 1,
      "격투": 1,
      "비행": 1,
      "독": 0.5,
      "땅": 1,
      "바위": 0.5,
      "벌레": 1,
      "고스트": 1,
      "강철": 1,
      "불꽃": 0.5,
      "물": 1,
      "풀": 1,
      "전기": 0,
      "에스퍼": 1,
      "악": 1
    },
    "dangerType": { "얼음": 4, "드래곤": 2, "페어리": 2 },
    "tera": ["드래곤", "땅"]
  },
  "코리갑": {
    "type": ["땅"],
    "safeType": {
      "노말": 1,
      "격투": 1,
      "비행": 1,
      "독": 0.5,
      "땅": 1,
      "바위": 0.5,
      "벌레": 1,
      "고스트": 1,
      "강철": 1,
      "불꽃": 1,
      "전기": 0,
      "에스퍼": 1,
      "드래곤": 1,
      "악": 1,
      "페어리": 1
    },
    "dangerType": { "물": 2, "풀": 2, "얼음": 2 },
    "tera": ["땅"]
  },
  "코뿌리": {
    "type": ["땅", "바위"],
    "safeType": {
      "노말": 0.5,
      "비행": 0.5,
      "독": 0.25,
      "바위": 0.5,
      "벌레": 1,
      "고스트": 1,
      "불꽃": 0.5,
      "전기": 0,
      "에스퍼": 1,
      "드래곤": 1,
      "악": 1,
      "페어리": 1
    },
    "dangerType": {
      "격투": 2,
      "땅": 2,
      "강철": 2,
      "물": 4,
      "풀": 4,
      "얼음": 2
    },
    "tera": ["땅", "바위"]
  },
  "코코리": {
    "type": ["땅"],
    "safeType": {
      "노말": 1,
      "격투": 1,
      "비행": 1,
      "독": 0.5,
      "땅": 1,
      "바위": 0.5,
      "벌레": 1,
      "고스트": 1,
      "강철": 1,
      "불꽃": 1,
      "전기": 0,
      "에스퍼": 1,
      "드래곤": 1,
      "악": 1,
      "페어리": 1
    },
    "dangerType": { "물": 2, "풀": 2, "얼음": 2 },
    "tera": ["땅"]
  },
  "탕구리": {
    "type": ["땅"],
    "safeType": {
      "노말": 1,
      "격투": 1,
      "비행": 1,
      "독": 0.5,
      "땅": 1,
      "바위": 0.5,
      "벌레": 1,
      "고스트": 1,
      "강철": 1,
      "불꽃": 1,
      "전기": 0,
      "에스퍼": 1,
      "드래곤": 1,
      "악": 1,
      "페어리": 1
    },
    "dangerType": { "물": 2, "풀": 2, "얼음": 2 },
    "tera": ["땅"]
  },
  "텅구리": {
    "type": ["땅"],
    "safeType": {
      "노말": 1,
      "격투": 1,
      "비행": 1,
      "독": 0.5,
      "땅": 1,
      "바위": 0.5,
      "벌레": 1,
      "고스트": 1,
      "강철": 1,
      "불꽃": 1,
      "전기": 0,
      "에스퍼": 1,
      "드래곤": 1,
      "악": 1,
      "페어리": 1
    },
    "dangerType": { "물": 2, "풀": 2, "얼음": 2 },
    "tera": ["땅"]
  },
  "텅구리 (알로라 텅구리)": {
    "type": ["땅"],
    "safeType": {
      "노말": 0,
      "격투": 0,
      "비행": 1,
      "독": 0.5,
      "벌레": 0.25,
      "강철": 0.5,
      "불꽃": 0.5,
      "풀": 0.5,
      "전기": 1,
      "에스퍼": 1,
      "얼음": 0.5,
      "드래곤": 1,
      "페어리": 0.5
    },
    "dangerType": { "땅": 2, "바위": 2, "고스트": 2, "물": 2, "악": 2 },
    "tera": ["땅"]
  },
  "토대부기": {
    "type": ["풀", "땅"],
    "safeType": {
      "노말": 1,
      "격투": 1,
      "독": 1,
      "땅": 0.5,
      "바위": 0.5,
      "고스트": 1,
      "강철": 1,
      "물": 1,
      "풀": 1,
      "전기": 0,
      "에스퍼": 1,
      "드래곤": 1,
      "악": 1,
      "페어리": 1
    },
    "dangerType": { "비행": 2, "벌레": 2, "불꽃": 2, "얼음": 4 },
    "tera": ["풀", "땅"]
  },
  "토오": {
    "type": ["독", "땅"],
    "safeType": {
      "노말": 1,
      "격투": 0.5,
      "비행": 1,
      "독": 0.25,
      "바위": 0.5,
      "벌레": 0.5,
      "고스트": 1,
      "강철": 1,
      "불꽃": 1,
      "풀": 1,
      "전기": 0,
      "드래곤": 1,
      "악": 1,
      "페어리": 0.5
    },
    "dangerType": { "땅": 2, "물": 2, "에스퍼": 2, "얼음": 2 },
    "tera": ["독", "땅"]
  },
  "토중몬": {
    "type": ["벌레", "땅"],
    "safeType": {
      "노말": 1,
      "격투": 0.5,
      "독": 0.5,
      "땅": 0.5,
      "바위": 1,
      "벌레": 1,
      "고스트": 1,
      "강철": 1,
      "풀": 1,
      "전기": 0,
      "에스퍼": 1,
      "드래곤": 1,
      "악": 1,
      "페어리": 1
    },
    "dangerType": { "비행": 2, "불꽃": 2, "물": 2, "얼음": 2 },
    "tera": ["벌레", "땅"]
  },
  "톱치": {
    "type": ["땅"],
    "safeType": {
      "노말": 1,
      "격투": 1,
      "비행": 1,
      "독": 0.5,
      "땅": 1,
      "바위": 0.5,
      "벌레": 1,
      "고스트": 1,
      "강철": 1,
      "불꽃": 1,
      "전기": 0,
      "에스퍼": 1,
      "드래곤": 1,
      "악": 1,
      "페어리": 1
    },
    "dangerType": { "물": 2, "풀": 2, "얼음": 2 },
    "tera": ["땅"]
  },
  "트리토돈": {
    "type": ["물", "땅"],
    "safeType": {
      "노말": 1,
      "격투": 1,
      "비행": 1,
      "독": 0.5,
      "땅": 1,
      "바위": 0.5,
      "벌레": 1,
      "고스트": 1,
      "강철": 0.5,
      "불꽃": 0.5,
      "물": 1,
      "전기": 0,
      "에스퍼": 1,
      "얼음": 1,
      "드래곤": 1,
      "악": 1,
      "페어리": 1
    },
    "dangerType": { "풀": 4 },
    "tera": ["물", "땅"]
  },
  "파르토": {
    "type": ["노말", "땅"],
    "safeType": {
      "노말": 1,
      "비행": 1,
      "독": 0.5,
      "땅": 1,
      "바위": 0.5,
      "벌레": 1,
      "고스트": 0,
      "강철": 1,
      "불꽃": 1,
      "전기": 0,
      "에스퍼": 1,
      "드래곤": 1,
      "악": 1,
      "페어리": 1
    },
    "dangerType": { "격투": 2, "물": 2, "풀": 2, "얼음": 2 },
    "tera": ["노말", "땅"]
  },
  "폭타": {
    "type": ["불꽃", "땅"],
    "safeType": {
      "노말": 1,
      "격투": 1,
      "비행": 1,
      "독": 0.5,
      "바위": 1,
      "벌레": 0.5,
      "고스트": 1,
      "강철": 0.5,
      "불꽃": 0.5,
      "풀": 1,
      "전기": 0,
      "에스퍼": 1,
      "얼음": 1,
      "드래곤": 1,
      "악": 1,
      "페어리": 0.5
    },
    "dangerType": { "땅": 2, "물": 4 },
    "tera": ["불꽃", "땅"]
  },
  "플라이곤": {
    "type": ["땅", "드래곤"],
    "safeType": {
      "노말": 1,
      "격투": 1,
      "비행": 1,
      "독": 0.5,
      "땅": 1,
      "바위": 0.5,
      "벌레": 1,
      "고스트": 1,
      "강철": 1,
      "불꽃": 0.5,
      "물": 1,
      "풀": 1,
      "전기": 0,
      "에스퍼": 1,
      "악": 1
    },
    "dangerType": { "얼음": 4, "드래곤": 2, "페어리": 2 },
    "tera": ["땅", "드래곤"]
  },
  "하마돈": {
    "type": ["땅"],
    "safeType": {
      "노말": 1,
      "격투": 1,
      "비행": 1,
      "독": 0.5,
      "땅": 1,
      "바위": 0.5,
      "벌레": 1,
      "고스트": 1,
      "강철": 1,
      "불꽃": 1,
      "전기": 0,
      "에스퍼": 1,
      "드래곤": 1,
      "악": 1,
      "페어리": 1
    },
    "dangerType": { "물": 2, "풀": 2, "얼음": 2 },
    "tera": ["땅"]
  },
  "한바이트": {
    "type": ["드래곤", "땅"],
    "safeType": {
      "노말": 1,
      "격투": 1,
      "비행": 1,
      "독": 0.5,
      "땅": 1,
      "바위": 0.5,
      "벌레": 1,
      "고스트": 1,
      "강철": 1,
      "불꽃": 0.5,
      "물": 1,
      "풀": 1,
      "전기": 0,
      "에스퍼": 1,
      "악": 1
    },
    "dangerType": { "얼음": 4, "드래곤": 2, "페어리": 2 },
    "tera": ["드래곤", "땅"]
  },
  "한카리아스": {
    "type": ["드래곤", "땅"],
    "safeType": {
      "노말": 1,
      "격투": 1,
      "비행": 1,
      "독": 0.5,
      "땅": 1,
      "바위": 0.5,
      "벌레": 1,
      "고스트": 1,
      "강철": 1,
      "불꽃": 0.5,
      "물": 1,
      "풀": 1,
      "전기": 0,
      "에스퍼": 1,
      "악": 1
    },
    "dangerType": { "얼음": 4, "드래곤": 2, "페어리": 2 },
    "tera": ["드래곤", "땅"]
  },
  "히포포타스": {
    "type": ["땅"],
    "safeType": {
      "노말": 1,
      "격투": 1,
      "비행": 1,
      "독": 0.5,
      "땅": 1,
      "바위": 0.5,
      "벌레": 1,
      "고스트": 1,
      "강철": 1,
      "불꽃": 1,
      "전기": 0,
      "에스퍼": 1,
      "드래곤": 1,
      "악": 1,
      "페어리": 1
    },
    "dangerType": { "물": 2, "풀": 2, "얼음": 2 },
    "tera": ["땅"]
  }
}
